sqlet/__init__.py
sqlet-0.1.2.dist-info/LICENSE
sqlet-0.1.2.dist-info/METADATA
sqlet-0.1.2.dist-info/WHEEL
sqlet-0.1.2.dist-info/top_level.txt
sqlet-0.1.2.dist-info/RECORD
