Metadata-Version: 2.1
Name: sqlet
Version: 0.1.2
Summary: SQL Easy Tools
Home-page: https://github.com/MieSlie/sqlet
Author: alextandr
Author-email: alextandr.lpt@yandex.ru
Project-URL: Documentation, https://github.com/MieSlie/sqlet/blob/main/README.md
Keywords: python database sqlite postgresql postgre sql
Classifier: Development Status :: 3 - Alpha
Classifier: Programming Language :: Python :: 3.10
Classifier: License :: OSI Approved :: MIT License
Classifier: Intended Audience :: Developers
Classifier: Topic :: Database
Classifier: Operating System :: OS Independent
Requires-Python: >=3.10
License-File: LICENSE
Requires-Dist: psycopg>=3.0
